keylogger/__init__.py
key_logger-0.0.1.dist-info/LICENSE
key_logger-0.0.1.dist-info/METADATA
key_logger-0.0.1.dist-info/WHEEL
key_logger-0.0.1.dist-info/top_level.txt
key_logger-0.0.1.dist-info/RECORD
